[
    {
        "arguments": [
            "c++",
            "-c",
            "-x",
            "c++",
            "-O0",
            "-g3",
            "-std=c++17",
            "-D",
            "NOCERTTEST",
            "-D_DEBUG",
            "-fPIC",
            "-I/home/dpriedel/projects/github/CollectEDGARData/src",
            "-I/usr/local/include",
            "-I/extra/boost/boost-1.67_gcc-7",
            "-I/extra/gcc/cpp-json/include/",
            "-march=native",
            "-o",
            "Debug_e2e/PathNameGenerator.o",
            "../CollectEDGARData/src/PathNameGenerator.cpp"
        ],
        "directory": "/home/dpriedel/projects/github/CollectEDGARData_Test",
        "file": "../CollectEDGARData/src/PathNameGenerator.cpp"
    },
    {
        "arguments": [
            "c++",
            "-c",
            "-x",
            "c++",
            "-O0",
            "-g3",
            "-std=c++17",
            "-D",
            "NOCERTTEST",
            "-D_DEBUG",
            "-fPIC",
            "-I/home/dpriedel/projects/github/CollectEDGARData/src",
            "-I/usr/local/include",
            "-I/extra/boost/boost-1.67_gcc-7",
            "-I/extra/gcc/cpp-json/include/",
            "-march=native",
            "-o",
            "Debug_e2e/HTTPS_Downloader.o",
            "../CollectEDGARData/src/HTTPS_Downloader.cpp"
        ],
        "directory": "/home/dpriedel/projects/github/CollectEDGARData_Test",
        "file": "../CollectEDGARData/src/HTTPS_Downloader.cpp"
    },
    {
        "arguments": [
            "c++",
            "-c",
            "-x",
            "c++",
            "-O0",
            "-g3",
            "-std=c++17",
            "-D",
            "NOCERTTEST",
            "-D_DEBUG",
            "-fPIC",
            "-I/home/dpriedel/projects/github/CollectEDGARData/src",
            "-I/usr/local/include",
            "-I/extra/boost/boost-1.67_gcc-7",
            "-I/extra/gcc/cpp-json/include/",
            "-march=native",
            "-o",
            "Debug_e2e/FormFileRetriever.o",
            "../CollectEDGARData/src/FormFileRetriever.cpp"
        ],
        "directory": "/home/dpriedel/projects/github/CollectEDGARData_Test",
        "file": "../CollectEDGARData/src/FormFileRetriever.cpp"
    },
    {
        "arguments": [
            "c++",
            "-c",
            "-x",
            "c++",
            "-O0",
            "-g3",
            "-std=c++17",
            "-D",
            "NOCERTTEST",
            "-D_DEBUG",
            "-fPIC",
            "-I/home/dpriedel/projects/github/CollectEDGARData/src",
            "-I/usr/local/include",
            "-I/extra/boost/boost-1.67_gcc-7",
            "-I/extra/gcc/cpp-json/include/",
            "-march=native",
            "-o",
            "Debug_e2e/EndToEnd_Test.o",
            "EndToEnd_Test.cpp"
        ],
        "directory": "/home/dpriedel/projects/github/CollectEDGARData_Test",
        "file": "EndToEnd_Test.cpp"
    },
    {
        "arguments": [
            "c++",
            "-c",
            "-x",
            "c++",
            "-O0",
            "-g3",
            "-std=c++17",
            "-D",
            "NOCERTTEST",
            "-D_DEBUG",
            "-fPIC",
            "-I/home/dpriedel/projects/github/CollectEDGARData/src",
            "-I/usr/local/include",
            "-I/extra/boost/boost-1.67_gcc-7",
            "-I/extra/gcc/cpp-json/include/",
            "-march=native",
            "-o",
            "Debug_unit/Unit_Test.o",
            "Unit_Test.cpp"
        ],
        "directory": "/home/dpriedel/projects/github/CollectEDGARData_Test",
        "file": "Unit_Test.cpp"
    },
    {
        "arguments": [
            "c++",
            "-c",
            "-x",
            "c++",
            "-O0",
            "-g3",
            "-std=c++17",
            "-D",
            "NOCERTTEST",
            "-D_DEBUG",
            "-fPIC",
            "-I/home/dpriedel/projects/github/CollectEDGARData/src",
            "-I/usr/local/include",
            "-I/extra/boost/boost-1.67_gcc-7",
            "-I/extra/gcc/cpp-json/include/",
            "-march=native",
            "-o",
            "Debug_e2e/TickerConverter.o",
            "../CollectEDGARData/src/TickerConverter.cpp"
        ],
        "directory": "/home/dpriedel/projects/github/CollectEDGARData_Test",
        "file": "../CollectEDGARData/src/TickerConverter.cpp"
    },
    {
        "arguments": [
            "c++",
            "-c",
            "-x",
            "c++",
            "-O0",
            "-g3",
            "-std=c++17",
            "-D",
            "NOCERTTEST",
            "-D_DEBUG",
            "-fPIC",
            "-I/home/dpriedel/projects/github/CollectEDGARData/src",
            "-I/usr/local/include",
            "-I/extra/boost/boost-1.67_gcc-7",
            "-I/extra/gcc/cpp-json/include/",
            "-march=native",
            "-o",
            "Debug_e2e/CollectEDGARApp.o",
            "../CollectEDGARData/src/CollectEDGARApp.cpp"
        ],
        "directory": "/home/dpriedel/projects/github/CollectEDGARData_Test",
        "file": "../CollectEDGARData/src/CollectEDGARApp.cpp"
    },
    {
        "arguments": [
            "c++",
            "-c",
            "-x",
            "c++",
            "-O0",
            "-g3",
            "-std=c++17",
            "-D",
            "NOCERTTEST",
            "-D_DEBUG",
            "-fPIC",
            "-I/home/dpriedel/projects/github/CollectEDGARData/src",
            "-I/usr/local/include",
            "-I/extra/boost/boost-1.67_gcc-7",
            "-I/extra/gcc/cpp-json/include/",
            "-march=native",
            "-o",
            "Debug_e2e/QuarterlyIndexFileRetriever.o",
            "../CollectEDGARData/src/QuarterlyIndexFileRetriever.cpp"
        ],
        "directory": "/home/dpriedel/projects/github/CollectEDGARData_Test",
        "file": "../CollectEDGARData/src/QuarterlyIndexFileRetriever.cpp"
    },
    {
        "arguments": [
            "c++",
            "-c",
            "-x",
            "c++",
            "-O0",
            "-g3",
            "-std=c++17",
            "-D",
            "NOCERTTEST",
            "-D_DEBUG",
            "-fPIC",
            "-I/home/dpriedel/projects/github/CollectEDGARData/src",
            "-I/usr/local/include",
            "-I/extra/boost/boost-1.67_gcc-7",
            "-I/extra/gcc/cpp-json/include/",
            "-march=native",
            "-o",
            "Debug_e2e/DailyIndexFileRetriever.o",
            "../CollectEDGARData/src/DailyIndexFileRetriever.cpp"
        ],
        "directory": "/home/dpriedel/projects/github/CollectEDGARData_Test",
        "file": "../CollectEDGARData/src/DailyIndexFileRetriever.cpp"
    }
]
